[
  {
    "delay_ms": 14.0,
    "decode_acc_mean": 0.5904761904761905,
    "decode_acc_sd": 0.19298937265866142,
    "decode_acc_n": 5,
    "decode_chance": 0.25,
    "gamma_coherence_mean": 0.3771383822569541,
    "gamma_coherence_sd": 0.07380615627357864,
    "gamma_coherence_n": 32,
    "granger_F_sr_mean": 88.08821798156879,
    "granger_F_sr_sd": 39.860560659906405,
    "granger_F_sr_n": 32,
    "transfer_entropy_mean": 0.08063852716392701,
    "transfer_entropy_sd": 0.026118864455416085,
    "transfer_entropy_n": 32,
    "sender_rate_hz_mean": 28.884375000000002,
    "sender_rate_hz_sd": 0.6129753398637718,
    "sender_rate_hz_n": 32,
    "receiver_rate_hz_mean": 30.937053571428574,
    "receiver_rate_hz_sd": 0.5720602427453094,
    "receiver_rate_hz_n": 32,
    "sender_gamma_power_mean": 0.4885988390942885,
    "sender_gamma_power_sd": 0.25309403834107064,
    "sender_gamma_power_n": 32,
    "receiver_gamma_power_mean": 0.6202128700449074,
    "receiver_gamma_power_sd": 0.42724556514260037,
    "receiver_gamma_power_n": 32
  },
  {
    "delay_ms": 16.0,
    "decode_acc_mean": 0.49523809523809526,
    "decode_acc_sd": 0.21782786688538439,
    "decode_acc_n": 5,
    "decode_chance": 0.25,
    "gamma_coherence_mean": 0.36378223044512753,
    "gamma_coherence_sd": 0.12177880590077926,
    "gamma_coherence_n": 32,
    "granger_F_sr_mean": 93.09367724760946,
    "granger_F_sr_sd": 47.10827055015377,
    "granger_F_sr_n": 32,
    "transfer_entropy_mean": 0.0708762157653827,
    "transfer_entropy_sd": 0.023708900261279888,
    "transfer_entropy_n": 32,
    "sender_rate_hz_mean": 28.884375000000002,
    "sender_rate_hz_sd": 0.6129753398637718,
    "sender_rate_hz_n": 32,
    "receiver_rate_hz_mean": 30.91294642857143,
    "receiver_rate_hz_sd": 0.4874104212022046,
    "receiver_rate_hz_n": 32,
    "sender_gamma_power_mean": 0.4885988390942885,
    "sender_gamma_power_sd": 0.25309403834107064,
    "sender_gamma_power_n": 32,
    "receiver_gamma_power_mean": 0.6046118489658743,
    "receiver_gamma_power_sd": 0.1890941200932603,
    "receiver_gamma_power_n": 32
  }
]